<?xml version="1.0" encoding="utf-8"?>
<odoo>
    <template id="quotation_arabic_document">
		             <t t-call="cells_report.cells_quotation_external_layout">
			 <t t-foreach="doc" t-as="o">
				<div class="page" style="padding-top:45px">
					<link rel="stylesheet" href="/cells_report/static/src/css/style.css"/>
					<link rel="stylesheet" href="/cells_report/static/src/scss/english.css"/>
					<link rel="stylesheet" href="/cells_report/static/src/scss/arabic.css"/>
					<t t-set="company" t-value="res_company"/>
					<div class="font">
					<div class="row mt32 mb32">
						 <div class="col-6" style="margin-top:-28pt;">
							 <table style="border:1pt solid grey;width:100%;font-size:12.4px; margin-top:-10px;" width="100%">
								 <tr style="border:1pt solid grey;width:100%;font-size:12.4px; margin-top:-10px;background-color:#DCDCDC">
									 <td style="text-align:left;font-family: 'English';padding-left:5px;">
										 <span class="text-right english"> Customer Information </span>
									 </td>
									 <td style="text-align:right;padding-right:5px;">
										 <span class="text-right arabic"> معلومات العميل </span>
									 </td>
								 </tr>
								 <tr>
									 <td colspan="2" class="text-left">
										 <span style="text-align:left;">اسم العميل - </span>
										 <span class="english" t-field="o.partner_id.name"/><br/>
										 <span class="arabic" t-field="o.partner_id.arabic_name"/>
									 </td>

								 </tr>
								 <tr>
									 <td colspan="2" class="text-left">
										 <span class="english" t-field="o.partner_id.city"/>
										 <span class="arabic" t-field="o.partner_id.state_id.name"/>
									 </td>
								 </tr>
								 <tr>
									 <td colspan="2" class="text-left">
										 <span class="english" t-field="o.partner_id.vat"/>
									 </td>
								 </tr>
							 </table>
						 </div>
						 <div class="col-6" style="margin-top:-28pt;">
							 <table style="border:1pt solid grey;width:100%;font-size:11px; margin-top:-10px;" width="100%">
								 <tr style="border:1pt solid grey;width:100%;font-size:12.4px; margin-top:-10px;background-color:#DCDCDC">
									 <td style="text-align:left;padding-left:5px;">
										 <span class="text-right english"> Supplier Information </span>
									 </td>
									 <td style="text-align:right;padding-right:5px;">
										 <span class="text-right arabic">معلومات المورد</span>
									 </td>
								 </tr>
								 <tr>
									 <td colspan="2" class="text-left">
										 <span class="english" t-field="o.company_id.name"/>
										 <span class="english" t-field="o.company_id.arabic_name"/>
									 </td>

								 </tr>
								 <tr>
									 <td colspan="2" class="text-left">
										 <span class="english">VAT # </span>
										 <span class="english" t-field="o.company_id.vat"/>
									 </td>
								 </tr>
								 <tr>
									 <td colspan="2" class="text-left">
										 <span class="english">WEBSITE # </span>
										 <span class="english" t-field="o.company_id.website"/>
									 </td>
								 </tr>
								 <tr>
									 <td colspan="2" class="text-left">
										 <span class="english">EMAIL # </span>
										 <span class="english" t-field="o.company_id.email"/>
									 </td>
								 </tr>
							 </table>
						 </div>
					</div>
					<br/>
						<table style="border:1pt solid grey;width:100%;margin-top:-10px;">
							<tr style="border:1pt solid grey;width:100%;font-size:12.4px; margin-top:-10px;background-color:#DCDCDC">
								<td style="border:1pt solid grey;">
									<span style="text-align:left; padding-left:5px;" class="english">Cust ID</span>
									<span style="text-align:right;padding-right:5px;float:right;!important;white-space: nowrap;" class="arabic">رقم العميل</span>
								</td>
								<td style="border:1pt solid grey;text-align:left;">
									<span style="text-align:left;padding-left:5px;" class="english">PO#</span>
									<span style="text-align:right;padding-right:5px;float:right;!important;white-space: nowrap;" class="arabic">رقم الشراء</span>
								</td>
								<td style="border:1pt solid grey;text-align:left;">
									<span style="text-align:left;padding-left:5px;" class="english">Delivery Method</span>
									<span style="text-align:right;padding-right:5px;float:right;!important;white-space: nowrap;" class="arabic">طريقة التوصيل</span>
								</td>
								<td style="border:1pt solid grey;text-align:left;">
									<span style="text-align:left;padding-left:5px;" class="english">SO#</span>
									<span style="text-align:right;padding-right:5px;float:right;!important;white-space: nowrap;" class="arabic">طلب المبيعات</span>
								</td>
							</tr>
							<tr style="border:1pt solid grey;width:100%;font-size:12.4px; margin-top:-10px;">
								<td style="border:1pt solid grey;text-align:center;">
									<span t-field="o.partner_id.id"/>
								</td>
								<td style="border:1pt solid grey;text-align:center;">
									<span t-field="o.client_order_ref"/>
								</td>
								<td style="border:1pt solid grey;text-align:center;">
									<span t-field="o.picking_policy"/>
								</td>
								<td style="border:1pt solid grey;text-align:center;">
									<span t-field="o.name"/>
								</td>
							</tr>
							<tr style="border:1pt solid grey;width:100%;font-size:12.4px; margin-top:-10px;background-color:#DCDCDC">
								<td style="border:1pt solid grey;text-align:left;" colspan="2">
									<span style="text-align:left; padding-left:5px;" class="english">Sales Rep</span>
									<span style="text-align:right;padding-right:5px;float:right;!important;white-space: nowrap;" class="arabic">مندوب مبيعات</span>
								</td>
								<td style="border:1pt solid grey;text-align:left;">
									<span style="text-align:left;padding-left:5px;" class="english">Payment Terms</span>
									<span style="text-align:right;padding-right:5px;float:right;!important;white-space: nowrap;" class="arabic">شروط الدفع</span>
								</td>
								<td style="border:1pt solid grey;text-align:left;">
									<span style="text-align:left;padding-left:5px;" class="english">Ship to City</span>
									<span style="text-align:right;padding-right:5px;float:right;!important;white-space: nowrap;" class="arabic">شحن إلى المدينة</span>
								</td>
							</tr>
							<tr style="border:1pt solid grey;width:100%;font-size:12.4px; margin-top:-10px;">
								<td style="border:1pt solid grey;text-align:center;" colspan="2">
									<span t-field="o.user_id"/>
								</td>
								<td style="border:1pt solid grey;text-align:center;">
									<span t-field="o.payment_term_id.name"/>
								</td>
								<td style="border:1pt solid grey;text-align:center;">
									<span> </span>
								</td>
							</tr>
						</table>


<!--					<table style="border:1pt solid grey;width:100%;margin-top:-10px;">-->
<!--						 <tr style="border:1pt solid grey;width:100%;font-size:12.4px; margin-top:-10px;">-->
<!--							 <td style="border:1pt solid grey; border-right:1pt solid white;">-->
<!--								 <span style="text-align:left;">Cust ID</span>-->
<!--							 </td>-->
<!--							 <td style="border:1pt solid grey; border-left:1pt solid white; text-align:right;" >-->
<!--								 <span class="text-align:right;">رقم العميل</span>-->
<!--							 </td>-->
<!--							 <td style="border:1pt solid grey; border-right:1pt solid white;">-->
<!--								 <span style="text-align:left;">PO#</span>-->
<!--							 </td>-->
<!--							 <td style="border:1pt solid grey; border-left:1pt solid white; text-align:right;" >-->
<!--								 <span style="text-align:right;">رقم الشراء</span>-->
<!--							 </td>-->
<!--							 <td style="border:1pt solid grey; border-right:1pt solid white;">-->
<!--								 <span style="text-align:left;">Delivery Method</span>-->
<!--							 </td>-->
<!--							 <td style="border:1pt solid grey; border-left:1pt solid white; text-align:right;" >-->
<!--								 <span style="text-align:right;">طريقة التوصيل</span>-->
<!--							 </td>-->
<!--							 <td style="border:1pt solid grey; border-right:1pt solid white;">-->
<!--								 <span style="text-align:left;">SO#</span>-->
<!--							 </td>-->
<!--							 <td style="border:1pt solid grey; border-left:1pt solid white; text-align:right;" >-->
<!--								 <span style="text-align:right;">طلب المبيعات</span>-->
<!--							 </td>-->
<!--						 </tr>-->
<!--						 <tr style="border:1pt solid grey;width:100%;font-size:12.4px; margin-top:-10px;">-->
<!--							 <td style="border:1pt solid grey;text-align:center;">-->
<!--								 <span t-field="o.partner_id.id"/>-->
<!--							 </td>-->
<!--							 <td style="border:1pt solid grey;text-align:center;">-->
<!--								 <span t-field="o.client_order_ref"/>-->
<!--							 </td>-->
<!--							 <td style="border:1pt solid grey;text-align:center;">-->
<!--								 <span t-field="o.picking_policy"/>-->
<!--							 </td>-->
<!--							 <td style="border:1pt solid grey;text-align:center;">-->
<!--								 <span t-field="o.name"/>-->
<!--							 </td>-->
<!--						 </tr>-->
<!--						 <tr style="border:1pt solid grey;width:100%;font-size:12.4px; margin-top:-10px;">-->
<!--							 <td style="border:1pt solid grey;text-align:center;" colspan="2">-->
<!--								  <span style="text-align:left;">Sales Rep</span><span style="text-align:right;">مندوب مبيعات</span>-->
<!--							 </td>-->
<!--							 <td style="border:1pt solid grey;text-align:center;">-->
<!--								  <span style="text-align:left;">payment Terms</span><span style="text-align:right;">شروط الدفع</span>-->
<!--							 </td>-->
<!--							 <td style="border:1pt solid grey;text-align:center;">-->
<!--								  <span style="text-align:left;">Ship to City</span><span style="text-align:right;">شحن إلى المدينة</span>-->
<!--							 </td>-->
<!--						 </tr>-->
<!--						 <tr style="border:1pt solid grey;width:100%;font-size:12.4px; margin-top:-10px;">-->
<!--							 <td style="border:1pt solid grey;text-align:center;" colspan="2">-->
<!--								 <span t-field="o.user_id"/>-->
<!--							 </td>-->
<!--							 <td style="border:1pt solid grey;text-align:center;">-->
<!--								 <span t-field="o.payment_term_id.name"></span>-->
<!--							 </td>-->
<!--							 <td style="border:1pt solid grey;text-align:center;">-->
<!--								 <span t-field="o.ship_to_city"/>-->
<!--							 </td>-->
<!--						 </tr>-->
<!--					</table>-->
					<br/>
						<div class="row mt32 mb32">
						<div class="col-12">
							<table style="border:1pt solid grey;width:100%;font-size:11px;" width="100%">
								 <tr style="border:1pt solid grey;width:100%;font-size:12.4px;">
									 <td style="text-align:left;" colspan="3">
										 Bank   :
										 <span t-field="o.bank_id.name" style="font-size: 12.4px;"/>
										  <td></td>
									 </td>
								 </tr>
<!--								 <tr style="border:1pt solid grey;width:100%;font-size:12.4px; margin-top:-10px;">-->
<!--									 <td style="text-align:left;" >-->
<!--										 <span t-field="o.company_id.bank_id.street" style="font-size: 12.4px;"/>-->
<!--									 </td>-->
<!--									 <td style="text-align:left;">-->
<!--										 <span t-field="o.company_id.bank_id.street2" style="font-size: 12.4px;"/>-->
<!--									 </td>-->
<!--									 <td style="text-align:left;">-->
<!--										 <span t-field="o.company_id.bank_id.country" style="font-size: 12.4px;"/>-->
<!--									 </td>-->
<!--								 </tr>-->
								 <tr style="border:1pt solid grey;width:100%;font-size:12.4px; margin-top:-10px;">
									 <td style="text-align:left;" colspan="3">
										 ACC NO 	:
										 <span t-field="o.bank_id.acc_no" style="font-size: 12.4px;"/>
									 </td>
								 </tr>
								<tr style="border:1pt solid grey;width:100%;font-size:12.4px; margin-top:-10px;">
									 <td style="text-align:left;" colspan="3">
										 IBAN   	:
										 <span t-field="o.bank_id.iban" style="font-size: 12.4px;"/>
									 </td>
								 </tr>
								<tr style="border:1pt solid grey;width:100%;font-size:12.4px; margin-top:-10px;">
									 <td style="text-align:left;" colspan="3">
										 SWIFT  	:
										 <span t-field="o.bank_id.swift" style="font-size: 12.4px;"/>
									 </td>
								 </tr>
							</table>
						</div>

<!--						<div class="col-2">-->
<!--							<img t-if="o.l10n_sa_qr_code_str"-->
<!--								t-att-src="'/report/barcode/?type=%s&amp;value=%s&amp;width=%s&amp;height=%s'%('QR', o.l10n_sa_qr_code_str, 70, 70)"/>-->
<!--						</div>-->
					</div>
					<br></br>
						<br></br>



					<table style="border:1pt solid grey;width:100%;color:black;font-size:12.4px; margin-top:-15pt; color:black;" class="table-condensed">
						<thead>
							<tr style="background-color:#DCDCDC">
								<td width="25%" style="border:1pt solid grey;text-align:center;padding:2pt; ">Items<br/><span class="arabic">العناصر</span></td>
<!--								<td style="border:1pt solid grey;text-align:center;padding:2pt;" >Item <br/> Description<br/><span class="arabic">وصف السلعة</span></td>-->
								<td style="border:1pt solid grey;text-align:center;padding:2pt;">Unit Price<br/><span class="arabic">سعر الوحدة</span></td>
								<td style="border:1pt solid grey;text-align:center;padding:2pt;width:7%">Quantity<br/><span class="arabic">الكمية</span></td>
<!--								<td style="border:1pt solid grey;text-align:center; width:10%;padding:2pt">Discount<br/><span class="arabic">خصومات</span></td>-->
<!--								<td style="border:1pt solid grey;text-align:center;padding:2pt;width:8%">Tax Rate<br/><span class="arabic">نسبة الضريبة</span></td>-->
<!--								<td style="border:1pt solid grey;text-align:center; width:10%;padding:2pt">Tax Amount<br/><span class="arabic">مبلغ الضريبة</span></td>-->
								<td style="border:1pt solid grey;text-align:center;padding:2pt;">Item Subtotal<br/>(Including VAT) <br/><span class="arabic">المجموع (شامل ضريبة القيمة المضافة)</span></td>
							</tr>
						</thead>
					 	<t t-set="tax_total" t-value="0"/>
					 	<t t-set="discount_total" t-value="0"/>
						<tbody class="invoice_tbody">
						 	<tr t-foreach="o.order_line" t-as="l">
						 		<t t-set="line_tax_total" t-value="0"/>
					 			<t t-foreach="l.tax_id" t-as="t">
					 				<t t-set="tax_total" t-value="round(tax_total + l.price_subtotal* t.amount/100, 2)"/>
					 				<t t-set="line_tax_total" t-value="line_tax_total + t.amount"/>
					 			</t>
					 			<t t-set="discount_total" t-value="discount_total + ((l.price_unit * l.product_uom_qty) - l.price_subtotal)"/>
						 		<td style="border-right:1pt solid grey;padding:3pt">
									<span class="text-right arabic" t-esc="l.product_id.arabic_name"/>
						 			<br/>
<!--						 		</td>-->
<!--								<td style="padding:3pt;border-right:1pt solid grey;text-align:right;">-->
								-<sapn t-field="l.product_id.arabic_desc"/>
						 		</td>
						 		<td style="border-right:1pt solid grey;width:13%;text-align:right;padding:3pt"><span t-field="l.price_unit"/></td>
						 		<td style="border-right:1pt solid grey;width:13%;text-align:center;padding:3pt"><span t-esc="'%.2f'%(l.product_uom_qty)"/></td>



<!--						 		<td style="border-right:1pt solid grey;text-align:right;padding:3pt;"  >-->
<!--	                                <span t-field="l.discount"/> %-->
<!--	                             </td>-->

<!--						 		<td style="border-right:1pt solid grey;padding:2pt;text-align:center;">-->
<!--						 			<t t-foreach="l.tax_id" t-as="t">-->
<!--						 				<span t-esc="'{0:,.2f}'.format(t.amount)"/> %-->
<!--					 				</t>-->
<!--					 				<span t-if="not l.tax_id">0.00 %</span>-->
<!--						 		</td>-->
<!--						 		<td style="padding:3pt;border-right:1pt solid grey;text-align:right;">-->
<!--						 			<t t-set="line_tax_total" t-value="l.price_subtotal*line_tax_total/100"/>-->
<!--						 			<span t-esc="'{0:,.2f}'.format(line_tax_total)"/>-->
<!--						 		</td>-->
						 		<td style="border-right:1pt solid grey;width:13%;text-align:right;padding:3pt" >
									<span t-esc="'{0:,.2f}'.format(l.price_total)"/>
			                    </td>
						 	</tr>

		               	</tbody>
					</table>

					<table style="border:1pt solid grey;width:100%;color:black;margin-top:8px;font-size:12.4px; color:black;" class="table table-bordered table-sm">
						<thead>
							<tr>
								<td width="33%" style="background-color:#DCDCDC;" class="text-left english">Total Amounts</td>
								<td width="33%" style="background-color:#DCDCDC;"/>
								<td colspan="2" width="34%" style="background-color:#DCDCDC;" class="text-right arabic">المبالغ الإجمالية</td>

							</tr>
							<t t-set="discount_before_total" t-value="doc.amount_untaxed + discount_total"/>
							<tr class="text-right">
								<td class="text-left" style="border-right:1pt solid grey;text-align:left;padding:3pt">Total (Excluding VAT)</td>
								<td class="text-right" style="border-right:1pt solid grey;text-align:right;padding:3pt">الإجمالي (غير شامل ضريبة القيمة المضافة)</td>
                                <td style="border-right:1pt solid grey;text-align:right;padding:3pt" class="text-right"><span t-esc="discount_before_total" t-options="{&quot;widget&quot;: &quot;monetary&quot;, &quot;display_currency&quot;: o.currency_id}"/></td>
							</tr>
							<tr class="text-right">
								<td class="text-left" style="border-right:1pt solid grey;text-align:left;padding:3pt">Discount</td>
								<td class="text-right" style="border-right:1pt solid grey;text-align:right;padding:3pt">مجموع الخصم</td>
								<td style="border-right:1pt solid grey;text-align:right;padding:3pt" class="text-right"><span t-esc="discount_total" t-options="{&quot;widget&quot;: &quot;monetary&quot;, &quot;display_currency&quot;: o.currency_id}"/></td>
							</tr>
							<tr class="text-right">
								<td class="text-left" style="border-right:1pt solid grey;text-align:left;padding:3pt">Total VAT</td>
								<td class="text-right" style="border-right:1pt solid grey;text-align:right;padding:3pt">إجمالي ضريبة القيمة المضافة</td>
								<td style="border-right:1pt solid grey;text-align:right;padding:3pt" class="text-right"><span t-esc="round(doc.amount_total - doc.amount_untaxed,2)" t-options="{&quot;widget&quot;: &quot;monetary&quot;, &quot;display_currency&quot;: o.currency_id}"/></td>
							</tr>
							<tr class="text-right">
								<td class="text-left english" style="border-right:1pt solid grey;text-align:left;padding:3pt">Total Amount</td>
								<td class="text-right arabic" style="border-right:1pt solid grey;text-align:right;padding:3pt">إجمالي المبلغ المستحق</td>
								<td style="border-right:1pt solid grey;text-align:right;padding:3pt" class="text-right"><span t-esc="doc.amount_total" t-options="{&quot;widget&quot;: &quot;monetary&quot;, &quot;display_currency&quot;: o.currency_id}"/></td>
							</tr>
						</thead>
					</table>

					<br/><br/>
					<t t-set="conditions" t-value="doc.get_conditions(doc.terms_category_id)"/>
						<span t-if="conditions">
						<table>
							<tr t-foreach="conditions" t-as="term">
								<t t-if="term.language == 'english'">
									<tr>
										<span style="font-size:15px; font-weight: bold;" t-field="term.name"/>
										<br/>
									</tr>
									<tr t-foreach="term.line_ids" t-as="val">
										<span style="color:black;" t-field="val.description"/>
										<br/>
									</tr>
								</t>
								<t t-if="term.language == 'arabic'">
									<div style="text-align:right;">
										<tr>
											<span style="font-size:15px; float:right; font-weight: bold;"
												  t-field="term.name"/>
											<br/>
										</tr>
										<tr t-foreach="term.line_ids" t-as="val">
											<span style="color:black; float:right;" t-field="val.description"/>
											<br/>
										</tr>
									</div>
								</t>

								<br/>
							</tr>
						</table>
					</span>

					<br/>

					<br/><br/>
					<span  style="padding-right:450pt;padding-top:30pt;">.............................Signature &amp;nbsp; إمضاء</span>

				</div>
				</div>
		</t>
	 	</t>

    </template>


    <template id="quotation_arabic">
	    <t t-call="web.html_container">
	        <t t-foreach="docs" t-as="doc">
	            <t t-call="cells_report.quotation_arabic_document"/>
	        </t>
	    </t>
	</template>


</odoo>